[
  {
    "_id": "5c0755a8857d7b1e000518ab",
    "index": 0,
    "guid": "42b018c9-4e38-4f34-bb50-bcc19348bfa1",
    "isActive": true,
    "balance": "$1,909.71",
    "picture": "http://placehold.it/32x32",
    "age": 23,
    "eyeColor": "brown",
    "name": "Macdonald Sargent",
    "gender": "male",
    "company": "EXTRAWEAR",
    "email": "macdonaldsargent@extrawear.com",
    "phone": "+1 (894) 400-2855",
    "address": "879 Allen Avenue, Brenton, Georgia, 7699",
    "about": "Commodo reprehenderit amet dolore sit. Excepteur ad proident quis nisi ea sit. Amet amet commodo velit occaecat id. Ipsum non in mollit ullamco nulla. Consectetur mollit ex et culpa ipsum incididunt non labore veniam. Deserunt eiusmod dolore sit occaecat sunt nulla duis ea reprehenderit.\r\n",
    "registered": "2016-10-05T10:41:21 +04:00",
    "latitude": 5.543681,
    "longitude": -49.634948,
    "tags": [
      "aliquip",
      "magna",
      "qui",
      "sit",
      "sit",
      "excepteur",
      "do"
    ],
    "friends": [
      {
        "id": 0,
        "name": "Jackson French"
      },
      {
        "id": 1,
        "name": "Osborne Snider"
      },
      {
        "id": 2,
        "name": "Mara Albert"
      }
    ],
    "greeting": "Hello, Macdonald Sargent! You have 6 unread messages.",
    "favoriteFruit": "banana"
  },
  {
    "_id": "5c0755a8386d9c7824e8200c",
    "index": 1,
    "guid": "70cff9bb-0d61-4a55-9a4e-c5068c4818cd",
    "isActive": true,
    "balance": "$1,535.46",
    "picture": "http://placehold.it/32x32",
    "age": 26,
    "eyeColor": "brown",
    "name": "Rosemary Santana",
    "gender": "female",
    "company": "ERSUM",
    "email": "rosemarysantana@ersum.com",
    "phone": "+1 (934) 590-2398",
    "address": "677 Harbor Court, Maplewood, Rhode Island, 1519",
    "about": "Aliquip elit proident ad veniam occaecat non ullamco. Do Lorem adipisicing ullamco dolor pariatur exercitation aute cupidatat duis. Sint irure duis minim culpa exercitation sint voluptate velit deserunt sint occaecat officia.\r\n",
    "registered": "2015-10-25T07:22:34 +04:00",
    "latitude": -84.45803,
    "longitude": 146.720384,
    "tags": [
      "reprehenderit",
      "fugiat",
      "mollit",
      "est",
      "ad",
      "sit",
      "exercitation"
    ],
    "friends": [
      {
        "id": 0,
        "name": "Susanna Mckee"
      },
      {
        "id": 1,
        "name": "Lolita Sullivan"
      },
      {
        "id": 2,
        "name": "Santiago Ochoa"
      }
    ],
    "greeting": "Hello, Rosemary Santana! You have 5 unread messages.",
    "favoriteFruit": "apple"
  },
  {
    "_id": "5c0755a8740a38a7c5cd618f",
    "index": 2,
    "guid": "81856093-5428-43be-b4d9-009102538965",
    "isActive": true,
    "balance": "$2,671.25",
    "picture": "http://placehold.it/32x32",
    "age": 26,
    "eyeColor": "brown",
    "name": "Bradford Ortega",
    "gender": "male",
    "company": "EXTRAGENE",
    "email": "bradfordortega@extragene.com",
    "phone": "+1 (991) 475-3129",
    "address": "502 Bergen Street, Laurelton, Texas, 6152",
    "about": "Incididunt reprehenderit dolor tempor elit est ad. Esse nulla do culpa laborum consequat. Nostrud velit fugiat officia ipsum ad reprehenderit in anim nulla nisi.\r\n",
    "registered": "2015-02-17T05:03:51 +05:00",
    "latitude": 79.682806,
    "longitude": 38.344082,
    "tags": [
      "esse",
      "aute",
      "ea",
      "deserunt",
      "sunt",
      "ullamco",
      "deserunt"
    ],
    "friends": [
      {
        "id": 0,
        "name": "Poole Turner"
      },
      {
        "id": 1,
        "name": "Dianne Sharp"
      },
      {
        "id": 2,
        "name": "Jodi Benson"
      }
    ],
    "greeting": "Hello, Bradford Ortega! You have 7 unread messages.",
    "favoriteFruit": "apple"
  },
  {
    "_id": "5c0755a86f0573b3f5e10931",
    "index": 3,
    "guid": "72407f4c-d102-477d-b89f-1325760d8ff1",
    "isActive": false,
    "balance": "$3,360.88",
    "picture": "http://placehold.it/32x32",
    "age": 23,
    "eyeColor": "green",
    "name": "Heath Jacobson",
    "gender": "male",
    "company": "COLUMELLA",
    "email": "heathjacobson@columella.com",
    "phone": "+1 (962) 494-2169",
    "address": "160 Essex Street, Statenville, Michigan, 8218",
    "about": "Pariatur fugiat tempor commodo labore commodo cillum laborum aute elit velit mollit sit veniam. Do ipsum fugiat aliquip consequat Lorem nostrud adipisicing est enim amet anim qui. Aliquip cupidatat irure proident elit quis minim.\r\n",
    "registered": "2016-02-02T02:54:09 +05:00",
    "latitude": 1.859376,
    "longitude": -22.163948,
    "tags": [
      "sint",
      "commodo",
      "dolore",
      "esse",
      "velit",
      "sint",
      "ex"
    ],
    "friends": [
      {
        "id": 0,
        "name": "Rivera Wilkinson"
      },
      {
        "id": 1,
        "name": "Dionne Carroll"
      },
      {
        "id": 2,
        "name": "Lizzie Cline"
      }
    ],
    "greeting": "Hello, Heath Jacobson! You have 6 unread messages.",
    "favoriteFruit": "apple"
  },
  {
    "_id": "5c0755a8d9871414d4d47534",
    "index": 4,
    "guid": "c161e005-9e97-4db6-a567-ce68ed2c1e89",
    "isActive": true,
    "balance": "$3,552.79",
    "picture": "http://placehold.it/32x32",
    "age": 30,
    "eyeColor": "blue",
    "name": "Vinson Hatfield",
    "gender": "male",
    "company": "CORMORAN",
    "email": "vinsonhatfield@cormoran.com",
    "phone": "+1 (997) 544-3917",
    "address": "781 Hutchinson Court, Nanafalia, Vermont, 541",
    "about": "Nisi fugiat esse nisi tempor officia eu. Excepteur irure exercitation aliquip esse sunt. Ut esse commodo nostrud exercitation esse cupidatat nostrud consectetur. Sint duis fugiat minim ea tempor in minim et. Cupidatat ullamco consectetur Lorem voluptate ut proident reprehenderit irure ex excepteur. Ullamco dolore mollit nostrud eiusmod dolor occaecat officia ex. Fugiat ipsum nostrud amet ea.\r\n",
    "registered": "2015-01-18T12:50:24 +05:00",
    "latitude": -53.805714,
    "longitude": 155.765359,
    "tags": [
      "minim",
      "laborum",
      "qui",
      "ad",
      "ea",
      "labore",
      "enim"
    ],
    "friends": [
      {
        "id": 0,
        "name": "Jeannine Mcdonald"
      },
      {
        "id": 1,
        "name": "French Rasmussen"
      },
      {
        "id": 2,
        "name": "Gale Carney"
      }
    ],
    "greeting": "Hello, Vinson Hatfield! You have 4 unread messages.",
    "favoriteFruit": "banana"
  },
  {
    "_id": "5c0755a84e7db0e396ccc2ec",
    "index": 5,
    "guid": "3f4bf7b5-a9bb-4e40-9d77-e06fd8e78e20",
    "isActive": false,
    "balance": "$2,860.54",
    "picture": "http://placehold.it/32x32",
    "age": 26,
    "eyeColor": "green",
    "name": "Kathryn Singleton",
    "gender": "female",
    "company": "QUARMONY",
    "email": "kathrynsingleton@quarmony.com",
    "phone": "+1 (827) 597-3658",
    "address": "557 Amherst Street, Odessa, Palau, 7816",
    "about": "Cupidatat sint commodo ipsum ut eiusmod ipsum magna exercitation officia labore eiusmod. Amet pariatur qui voluptate consequat esse proident. Ex velit qui ipsum reprehenderit in sint eu anim adipisicing. Laboris in et reprehenderit laboris adipisicing do dolor qui amet pariatur nisi exercitation fugiat. Incididunt pariatur Lorem velit duis fugiat irure cupidatat. Enim minim ea irure tempor irure velit. Labore do reprehenderit laboris anim enim sint irure nostrud sint.\r\n",
    "registered": "2014-02-18T12:19:26 +05:00",
    "latitude": -66.597319,
    "longitude": 22.699741,
    "tags": [
      "consectetur",
      "exercitation",
      "officia",
      "ad",
      "ipsum",
      "voluptate",
      "pariatur"
    ],
    "friends": [
      {
        "id": 0,
        "name": "Lila Russell"
      },
      {
        "id": 1,
        "name": "Parrish Galloway"
      },
      {
        "id": 2,
        "name": "White Hayden"
      }
    ],
    "greeting": "Hello, Kathryn Singleton! You have 5 unread messages.",
    "favoriteFruit": "banana"
  },
  {
    "_id": "5c0755a8482cce5844746a17",
    "index": 6,
    "guid": "443d8a21-462c-4871-999e-ed939415a0db",
    "isActive": true,
    "balance": "$3,957.56",
    "picture": "http://placehold.it/32x32",
    "age": 22,
    "eyeColor": "green",
    "name": "Oconnor Abbott",
    "gender": "male",
    "company": "ZILLATIDE",
    "email": "oconnorabbott@zillatide.com",
    "phone": "+1 (874) 473-2031",
    "address": "815 Sumpter Street, Yukon, Alaska, 5789",
    "about": "Laborum aute sit ullamco ut laborum labore occaecat dolore minim tempor elit eiusmod nulla. Proident duis in pariatur et deserunt duis enim in eu ea proident elit deserunt cupidatat. Incididunt non eu mollit deserunt veniam aliqua occaecat. Nulla laborum consequat tempor dolore anim veniam proident eiusmod consequat ad adipisicing anim. Ullamco laborum ex enim ullamco aute proident aute. Adipisicing do dolor amet magna magna consectetur officia qui id. Aute pariatur sit ea duis cillum deserunt officia adipisicing voluptate.\r\n",
    "registered": "2018-12-03T11:36:11 +05:00",
    "latitude": -51.307938,
    "longitude": -61.885092,
    "tags": [
      "et",
      "qui",
      "magna",
      "laboris",
      "ex",
      "aliqua",
      "excepteur"
    ],
    "friends": [
      {
        "id": 0,
        "name": "Browning Wilkerson"
      },
      {
        "id": 1,
        "name": "Travis Sheppard"
      },
      {
        "id": 2,
        "name": "Lawson Kirby"
      }
    ],
    "greeting": "Hello, Oconnor Abbott! You have 6 unread messages.",
    "favoriteFruit": "apple"
  }
]